CHANGES.txt
COPYING
COPYING.LESSER
LICENSE
MANIFEST.in
README.txt
VERSION.txt
setup.py
krpc/__init__.py
krpc/attributes.py
krpc/client.py
krpc/connection.py
krpc/decoder.py
krpc/encoder.py
krpc/error.py
krpc/event.py
krpc/platform.py
krpc/py.typed
krpc/service.py
krpc/stream.py
krpc/streammanager.py
krpc/types.py
krpc/utils.py
krpc/version.py
krpc.egg-info/PKG-INFO
krpc.egg-info/SOURCES.txt
krpc.egg-info/dependency_links.txt
krpc.egg-info/requires.txt
krpc.egg-info/top_level.txt
krpc/schema/KRPC_pb2.py
krpc/schema/KRPC_pb2.pyi
krpc/schema/__init__.py
krpc/services/__init__.py
krpc/services/dockingcamera.py
krpc/services/drawing.py
krpc/services/infernalrobotics.py
krpc/services/kerbalalarmclock.py
krpc/services/krpc.py
krpc/services/lidar.py
krpc/services/remotetech.py
krpc/services/spacecenter.py
krpc/services/testservice.py
krpc/services/ui.py
krpc/test/__init__.py
krpc/test/servertestcase.py
krpc/test/test_attributes.py
krpc/test/test_client.py
krpc/test/test_connection.py
krpc/test/test_decoder.py
krpc/test/test_documentation.py
krpc/test/test_encodedecode.py
krpc/test/test_encoder.py
krpc/test/test_event.py
krpc/test/test_objects.py
krpc/test/test_performance.py
krpc/test/test_platform.py
krpc/test/test_snake_case.py
krpc/test/test_stream.py
krpc/test/test_threading.py
krpc/test/test_types.py
krpc/test/schema/__init__.py