Metadata-Version: 2.1
Name: krpc
Version: 0.5.4
Summary: Client library for kRPC, a Remote Procedure Call server for Kerbal Space Program
Home-page: https://krpc.github.io/krpc
Author: djungelorm
Author-email: djungelorm@users.noreply.github.com
License: GNU LGPL v3
Platform: UNKNOWN
Classifier: Development Status :: 5 - Production/Stable
Classifier: Intended Audience :: End Users/Desktop
Classifier: License :: OSI Approved :: GNU Lesser General Public License v3 (LGPLv3)
Classifier: Natural Language :: English
Classifier: Programming Language :: Python :: 3
Classifier: Operating System :: Microsoft :: Windows
Classifier: Operating System :: Unix
Classifier: Topic :: Communications
Classifier: Topic :: Games/Entertainment :: Simulation
Classifier: Topic :: Internet
Requires-Python: >=3.7
License-File: LICENSE
License-File: COPYING
License-File: COPYING.LESSER
